zeroproof/__init__.py
zeroproof/client.py
zeroproof/exceptions.py
zeroproof/models.py
zeroproof/py.typed
zeroproof-0.2.0.dist-info/METADATA
zeroproof-0.2.0.dist-info/WHEEL
zeroproof-0.2.0.dist-info/licenses/LICENSE
zeroproof-0.2.0.dist-info/RECORD
