Metadata-Version: 2.4
Name: zeroproof
Version: 0.2.0
Summary: Python SDK for ZeroProof AI verification API - Secure your agentic e-commerce ecosystem
Project-URL: Homepage, https://github.com/jacobweiss2305/zeroproof
Project-URL: Documentation, https://docs.zeroproofai.com
Project-URL: Repository, https://github.com/jacobweiss2305/zeroproof
Project-URL: Bug Tracker, https://github.com/jacobweiss2305/zeroproof/issues
Author-email: ZeroProof AI <support@zeroproofai.com>
Maintainer-email: ZeroProof AI <support@zeroproofai.com>
License: MIT
License-File: LICENSE
Keywords: agent,ai,ecommerce,security,verification,zero-knowledge-proof,zeroproof,zkp
Classifier: Development Status :: 3 - Alpha
Classifier: Intended Audience :: Developers
Classifier: License :: OSI Approved :: MIT License
Classifier: Programming Language :: Python :: 3
Classifier: Programming Language :: Python :: 3.8
Classifier: Programming Language :: Python :: 3.9
Classifier: Programming Language :: Python :: 3.10
Classifier: Programming Language :: Python :: 3.11
Classifier: Programming Language :: Python :: 3.12
Classifier: Topic :: Security :: Cryptography
Classifier: Topic :: Software Development :: Libraries :: Python Modules
Requires-Python: >=3.8
Requires-Dist: requests>=2.25.0
Provides-Extra: dev
Requires-Dist: black>=22.0.0; extra == 'dev'
Requires-Dist: flake8>=4.0.0; extra == 'dev'
Requires-Dist: mypy>=0.950; extra == 'dev'
Requires-Dist: pytest-cov>=4.0.0; extra == 'dev'
Requires-Dist: pytest>=7.0.0; extra == 'dev'
Requires-Dist: twine>=4.0.0; extra == 'dev'
